MANIFEST.in
README.md
pyproject.toml
setup.py
amuse_mesa_r2208.egg-info/PKG-INFO
amuse_mesa_r2208.egg-info/SOURCES.txt
amuse_mesa_r2208.egg-info/dependency_links.txt
amuse_mesa_r2208.egg-info/requires.txt
amuse_mesa_r2208.egg-info/top_level.txt
src/amuse/community/mesa_r2208/.gitignore
src/amuse/community/mesa_r2208/Makefile
src/amuse/community/mesa_r2208/__init__.py
src/amuse/community/mesa_r2208/_version.py
src/amuse/community/mesa_r2208/build_mesa.py
src/amuse/community/mesa_r2208/download.py
src/amuse/community/mesa_r2208/install
src/amuse/community/mesa_r2208/interface.f
src/amuse/community/mesa_r2208/interface.py
src/amuse/community/mesa_r2208/patch_files.py
src/amuse/community/mesa_r2208/test_jina.f
src/amuse/community/mesa_r2208/zams_z20m3.data.gz
src/amuse/community/mesa_r2208/data/README.txt
src/amuse/community/mesa_r2208/data/input/AMUSE_inlist
src/amuse/community/mesa_r2208/data/input/star_data/starting_models/empty.txt
src/amuse/community/mesa_r2208/mesa_reqs/Makefile
src/amuse/community/mesa_r2208/mesa_reqs/README
src/amuse/community/mesa_r2208/mesa_reqs/makefile_header
src/amuse/community/mesa_r2208/mesa_reqs/makefile_include
src/amuse/community/mesa_r2208/patches/alert
src/amuse/community/mesa_r2208/patches/build
src/amuse/community/mesa_r2208/patches/definitions
src/amuse/community/mesa_r2208/patches/filelen
src/amuse/community/mesa_r2208/patches/kaptestinit
src/amuse/community/mesa_r2208/patches/openmp
src/amuse/community/mesa_r2208/patches/series
src/amuse/community/mesa_r2208/patches/test
src/amuse/community/mesa_r2208/patches/warningisnoterror
support/__init__.py
support/classifiers.py
support/config.py
support/generate_main.py
support/getsp.class
support/getsp.java
support/misc.py
support/setup_codes.py
support/version.py